mixam_public_api/__init__.py
mixam_public_api/models.py
mixam_python_public_api-0.0.2.dist-info/licenses/AUTHORS.rst
mixam_python_public_api-0.0.2.dist-info/licenses/LICENSE.txt
mixam_python_public_api-0.0.2.dist-info/METADATA
mixam_python_public_api-0.0.2.dist-info/WHEEL
mixam_python_public_api-0.0.2.dist-info/top_level.txt
mixam_python_public_api-0.0.2.dist-info/RECORD
