Metadata-Version: 2.4
Name: mixam-python-public-api
Version: 0.0.2
Summary: Auto-generated Pydantic models for Mixam Public API
Author: Ashley Swatton
License: MIT
Classifier: Programming Language :: Python :: 3
Classifier: License :: OSI Approved :: MIT License
Classifier: Development Status :: 4 - Beta
Requires-Python: >=3.11
License-File: LICENSE.txt
License-File: AUTHORS.rst
Requires-Dist: pydantic<3,>=2
Dynamic: license-file
